tests/__init__.py
tests/blocks.py
tests/constants.py
tests/models.py
tests/management/__init__.py
tests/management/commands/__init__.py
tests/management/commands/init.py
tests/migrations/0001_initial.py
tests/migrations/__init__.py
wagtailyoast/__init__.py
wagtailyoast/context.py
wagtailyoast/edit_handlers.py
wagtailyoast/wagtail_hooks.py
wagtailyoast/static/wagtailyoast/dist/css/styles0.0.1.css
wagtailyoast/static/wagtailyoast/dist/css/styles0.0.10.css
wagtailyoast/static/wagtailyoast/dist/css/styles0.0.2.css
wagtailyoast/static/wagtailyoast/dist/css/styles0.0.3.css
wagtailyoast/static/wagtailyoast/dist/css/styles0.0.5.css
wagtailyoast/static/wagtailyoast/dist/css/styles0.0.6.css
wagtailyoast/static/wagtailyoast/dist/css/styles0.0.7.css
wagtailyoast/static/wagtailyoast/dist/css/styles0.0.8.css
wagtailyoast/static/wagtailyoast/dist/css/styles0.0.9.css
wagtailyoast/static/wagtailyoast/dist/js/styles0.0.1.js
wagtailyoast/static/wagtailyoast/dist/js/styles0.0.10.js
wagtailyoast/static/wagtailyoast/dist/js/styles0.0.2.js
wagtailyoast/static/wagtailyoast/dist/js/styles0.0.3.js
wagtailyoast/static/wagtailyoast/dist/js/styles0.0.5.js
wagtailyoast/static/wagtailyoast/dist/js/styles0.0.6.js
wagtailyoast/static/wagtailyoast/dist/js/styles0.0.7.js
wagtailyoast/static/wagtailyoast/dist/js/styles0.0.8.js
wagtailyoast/static/wagtailyoast/dist/js/styles0.0.9.js
wagtailyoast/static/wagtailyoast/dist/js/yoastanalysis0.0.1.js
wagtailyoast/static/wagtailyoast/dist/js/yoastanalysis0.0.10.js
wagtailyoast/static/wagtailyoast/dist/js/yoastanalysis0.0.2.js
wagtailyoast/static/wagtailyoast/dist/js/yoastanalysis0.0.3.js
wagtailyoast/static/wagtailyoast/dist/js/yoastanalysis0.0.5.js
wagtailyoast/static/wagtailyoast/dist/js/yoastanalysis0.0.6.js
wagtailyoast/static/wagtailyoast/dist/js/yoastanalysis0.0.7.js
wagtailyoast/static/wagtailyoast/dist/js/yoastanalysis0.0.8.js
wagtailyoast/static/wagtailyoast/dist/js/yoastanalysis0.0.9.js
wagtailyoast/static/wagtailyoast/dist/js/yoastworker0.0.1.js
wagtailyoast-0.0.10.dist-info/LICENSE
wagtailyoast-0.0.10.dist-info/METADATA
wagtailyoast-0.0.10.dist-info/WHEEL
wagtailyoast-0.0.10.dist-info/top_level.txt
wagtailyoast-0.0.10.dist-info/RECORD
