Metadata-Version: 2.1
Name: wagtailyoast
Version: 0.0.10
Summary: Yoast For Wagtail
Home-page: https://github.com/Aleksi44/wagtailyoast
Author: Alexis Le Baron
Author-email: alexis@stationspatiale.com
License: GPL-3.0
Keywords: wagtail yoast seo
Platform: linux
Classifier: Environment :: Web Environment
Classifier: Intended Audience :: Developers
Classifier: Programming Language :: Python
Classifier: Programming Language :: Python :: 3
Classifier: Programming Language :: Python :: 3.6
Classifier: Programming Language :: Python :: 3.7
Classifier: Programming Language :: Python :: 3.8
Classifier: Operating System :: OS Independent
Classifier: Topic :: Software Development
